opentelemetry/instrumentation/arq/__init__.py
opentelemetry/instrumentation/arq/package.py
opentelemetry/instrumentation/arq/version.py
opentelemetry_instrumentation_arq-0.50b1.dist-info/licenses/LICENSE
opentelemetry_instrumentation_arq-0.50b1.dist-info/METADATA
opentelemetry_instrumentation_arq-0.50b1.dist-info/WHEEL
opentelemetry_instrumentation_arq-0.50b1.dist-info/entry_points.txt
opentelemetry_instrumentation_arq-0.50b1.dist-info/top_level.txt
opentelemetry_instrumentation_arq-0.50b1.dist-info/RECORD
